whyis_author_affiliation_agent/__init__.py
whyis_author_affiliation_agent/affiliation_agent.py
whyis_author_affiliation_agent/request_affiliation.py
whyis_author_affiliation_agent/test_Author_Affiliation_Agent.py
whyis_author_affiliation_agent-0.0.1.data/scripts/authoraffiliationsetup
whyis_author_affiliation_agent-0.0.1.data/scripts/authoraffiliationtest
whyis_author_affiliation_agent-0.0.1.dist-info/LICENSE
whyis_author_affiliation_agent-0.0.1.dist-info/METADATA
whyis_author_affiliation_agent-0.0.1.dist-info/WHEEL
whyis_author_affiliation_agent-0.0.1.dist-info/top_level.txt
whyis_author_affiliation_agent-0.0.1.dist-info/RECORD
