Metadata-Version: 2.1
Name: whyis-author-affiliation-agent
Version: 0.0.1
Summary: Author and Affiliation retrieval for Whyis
Home-page: https://github.com/roryschadler/whyis_author_affiliation_agent
Author: Rory Schadler
Author-email: rory.h.schadler.21@dartmouth.edu
License: UNKNOWN
Platform: UNKNOWN
Classifier: Programming Language :: Python :: 3
Classifier: License :: OSI Approved :: MIT License
Classifier: Operating System :: OS Independent
Requires-Python: >=3.5.2
Requires-Dist: rdflib
Requires-Dist: geopy
